{
    "NEWS_SKIP_EVENTS": ["NFP", "CPI", "ECB"],
    "OCAE": {
        "IB_START": "09:00",
        "IB_END": "09:30",
        "IB_TZ": "America/New_York",
        "IB_WAIT": 0,
        "TRADE_WINDOW": 120,
        "RR_TARGET": 1.0,
        "STOP_MODE": "ib_start",
        "TSL_TARGET": 1.0,
        "TSL_SL": 1.0,
        "MIN_SL_PCT": 0.0015,
        "IB_BUFFER_PCT": 0.1,
        "MAX_DISTANCE_PCT": 1.0,
        "FRACTAL_BE_ENABLED": true,
        "FRACTAL_TSL_ENABLED": true,
        "FVG_BE_ENABLED": false,
        "M2_BOS_CHART_ENABLED": true
    },
    "TCWE": {
        "IB_START": "09:00",
        "IB_END": "09:30",
        "IB_TZ": "America/New_York",
        "IB_WAIT": 0,
        "TRADE_WINDOW": 120,
        "RR_TARGET": 1.0,
        "STOP_MODE": "ib_start",
        "TSL_TARGET": 1.0,
        "TSL_SL": 1.0,
        "MIN_SL_PCT": 0.0015,
        "IB_BUFFER_PCT": 0.1,
        "MAX_DISTANCE_PCT": 1.0,
        "FRACTAL_BE_ENABLED": true,
        "FRACTAL_TSL_ENABLED": true,
        "FVG_BE_ENABLED": false,
        "M2_BOS_CHART_ENABLED": true
    },
    "Reverse": {
        "IB_START": "09:00",
        "IB_END": "09:30",
        "IB_TZ": "America/New_York",
        "IB_WAIT": 0,
        "TRADE_WINDOW": 120,
        "RR_TARGET": 1.0,
        "STOP_MODE": "ib_start",
        "TSL_TARGET": 1.0,
        "TSL_SL": 1.0,
        "MIN_SL_PCT": 0.0015,
        "IB_BUFFER_PCT": 0.0,
        "MAX_DISTANCE_PCT": 1.0,
        "FRACTAL_BE_ENABLED": true,
        "FRACTAL_TSL_ENABLED": true,
        "FVG_BE_ENABLED": false,
        "M2_BOS_CHART_ENABLED": true
    },
    "REV_RB": {
        "IB_START": "09:00",
        "IB_END": "09:30",
        "IB_TZ": "America/New_York",
        "IB_WAIT": 0,
        "TRADE_WINDOW": 120,
        "RR_TARGET": 1.0,
        "TSL_TARGET": 1.0,
        "TSL_SL": 1.0,
        "MIN_SL_PCT": 0.00,
        "REV_RB_ENABLED": false,
        "IB_BUFFER_PCT": 0.0,
        "MAX_DISTANCE_PCT": 1.0,
        "FRACTAL_BE_ENABLED": true,
        "FRACTAL_TSL_ENABLED": true,
        "FVG_BE_ENABLED": false,
        "M2_BOS_CHART_ENABLED": true
    },
    "BTIB": {
        "BTIB_ENABLED": false,
        "BTIB_SL_MODE": "fractal_2m",
        "CORE_CUTOFF_MIN": 40,
        "EXTENSION_PCT": 1.0,
        "RR_TARGET": 1.0,
        "TSL_TARGET": 1.0,
        "TSL_SL": 1.0,
        "MIN_SL_PCT": 0.00,
        "FRACTAL_BE_ENABLED": true,
        "FRACTAL_TSL_ENABLED": true,
        "FVG_BE_ENABLED": false,
        "M2_BOS_CHART_ENABLED": true
    }
}
